pdfpaper/__init__.py
pdfpaper/main.py
pdfpaper-0.1.1.dist-info/LICENSE
pdfpaper-0.1.1.dist-info/WHEEL
pdfpaper-0.1.1.dist-info/METADATA
pdfpaper-0.1.1.dist-info/RECORD
